{
    "learning_records": [
      {
        "img": "https://w7.pngwing.com/pngs/290/579/png-transparent-html-html-logo-html-5-html-five-logo-html-5-logo-programming-langugae-3d-icon-thumbnail.png",
        "title": "My HTML & CSS Page",
        "pagelink": "https://linwinashwinlin.github.io/React-Learning/",
        "repolink": "https://github.com"
      },
        {
        "img" : "https://www.google.com/url?sa=i&url=https%3A%2F%2Fwww.flaticon.com%2Ffree-icon%2Fjs_5968292&psig=AOvVaw2EtrKMOLd3SOaVcoFZv7Q1&ust=1723622446173000&source=images&cd=vfe&opi=89978449&ved=0CBEQjRxqFwoTCPDmuo7A8YcDFQAAAAAdAAAAABAE"
        "title": "My JS Validation",
        "pagelink": "https://linwinashwinlin.github.io/ashwin-learn-JS/",
        "repolink": "https://github.com"
      }
  ]
}
